adachi_resource_assistant/__init__.py
adachi_resource_assistant/names.py
adachi_resource_assistant/utils.py
tests/__init__.py
tests/test_true.py
adachi_resource_assistant-3.0.2.dist-info/LICENSE
adachi_resource_assistant-3.0.2.dist-info/METADATA
adachi_resource_assistant-3.0.2.dist-info/WHEEL
adachi_resource_assistant-3.0.2.dist-info/entry_points.txt
adachi_resource_assistant-3.0.2.dist-info/top_level.txt
adachi_resource_assistant-3.0.2.dist-info/zip-safe
adachi_resource_assistant-3.0.2.dist-info/RECORD
