Metadata-Version: 2.1
Name: adachi-resource-assistant
Version: 3.0.2
Summary: A resource assistant for Adachi-BOT
Home-page: https://github.com/Mark9804/adachi-resource-assistant
Download-URL: https://pypi.org/project/adachi_resource_assistant
Author: Mark9804, Qin Fandong
Author-email: shell_way@foxmail.com
License: MIT License
Platform: Any
Classifier: Programming Language :: Python
Classifier: Programming Language :: Python :: 3
Classifier: Programming Language :: Python :: 3.8
Classifier: Programming Language :: Python :: 3.9
Classifier: Programming Language :: Python :: 3.10
Classifier: Programming Language :: Python :: 3 :: Only
Classifier: License :: OSI Approved :: MIT License
Classifier: Operating System :: OS Independent
License-File: LICENSE
Requires-Dist: Pillow (==9.1.1)
Requires-Dist: PyYAML (==6.0)
Requires-Dist: requests (==2.28.0)
